[
  {
    "source": "ow",
    "current": {
      "icon": "clear-day",
      "temp": 15,
      "summary": "clear sky",
      "windDir": 60,
      "humidity": 63,
      "pressure": 1026,
      "feelsLike": 14,
      "windSpeed": 3.6,
      "cloudCover": 0,
      "visibility": 10,
      "percipitation": 0
    },
    "forecast": [
      {
        "date": 1651143600,
        "maxTemp": 21,
        "minTemp": 8,
        "sunrise": "06:36",
        "sunset": "21:01",
        "summary": "scattered clouds",
        "windSpeed": 5.16,
        "windDir": 73,
        "percipitation": 0,
        "humidity": 53,
        "pressure": 1026,
        "cloudCover": 27,
        "dewPoint": 7,
        "chancePrecipitation": 0,
        "chanceRain": 0,
        "chanceSnow": 0,
        "chanceThunder": 0,
        "chanceSleet": 0,
        "icon": "cloudy",
        "day": "Thursday",
        "dayShort": "Thu"
      },
      {
        "date": 1651230000,
        "maxTemp": 18,
        "minTemp": 10,
        "sunrise": "06:34",
        "sunset": "21:03",
        "summary": "overcast clouds",
        "windSpeed": 4.51,
        "windDir": 15,
        "percipitation": 0,
        "humidity": 62,
        "pressure": 1028,
        "cloudCover": 100,
        "dewPoint": 7,
        "chancePrecipitation": 1,
        "chanceRain": 0,
        "chanceSnow": 0,
        "chanceThunder": 0,
        "chanceSleet": 0,
        "icon": "cloudy",
        "day": "Friday",
        "dayShort": "Fri"
      },
      {
        "date": 1651316400,
        "maxTemp": 17,
        "minTemp": 7,
        "sunrise": "06:33",
        "sunset": "21:04",
        "summary": "clear sky",
        "windSpeed": 4.44,
        "windDir": 15,
        "percipitation": 0,
        "humidity": 46,
        "pressure": 1026,
        "cloudCover": 2,
        "dewPoint": 3,
        "chancePrecipitation": 0,
        "chanceRain": 0,
        "chanceSnow": 0,
        "chanceThunder": 0,
        "chanceSleet": 0,
        "icon": "clear-day",
        "day": "Saturday",
        "dayShort": "Sat"
      },
      {
        "date": 1651402800,
        "maxTemp": 18,
        "minTemp": 9,
        "sunrise": "06:31",
        "sunset": "21:06",
        "summary": "overcast clouds",
        "windSpeed": 3,
        "windDir": 5,
        "percipitation": 0,
        "humidity": 40,
        "pressure": 1022,
        "cloudCover": 100,
        "dewPoint": 3,
        "chancePrecipitation": 0,
        "chanceRain": 0,
        "chanceSnow": 0,
        "chanceThunder": 0,
        "chanceSleet": 0,
        "icon": "cloudy",
        "day": "Sunday",
        "dayShort": "Sun"
      },
      {
        "date": 1651489200,
        "maxTemp": 19,
        "minTemp": 10,
        "sunrise": "06:29",
        "sunset": "21:07",
        "summary": "light rain",
        "windSpeed": 4.45,
        "windDir": 29,
        "percipitation": 0.12,
        "humidity": 48,
        "pressure": 1018,
        "cloudCover": 100,
        "dewPoint": 7,
        "chancePrecipitation": 31,
        "chanceRain": 0,
        "chanceSnow": 0,
        "chanceThunder": 0,
        "chanceSleet": 0,
        "icon": "rain",
        "day": "Monday",
        "dayShort": "Mon"
      },
      {
        "date": 1651575600,
        "maxTemp": 19,
        "minTemp": 9,
        "sunrise": "06:28",
        "sunset": "21:09",
        "summary": "few clouds",
        "windSpeed": 4.98,
        "windDir": 25,
        "percipitation": 0,
        "humidity": 42,
        "pressure": 1018,
        "cloudCover": 14,
        "dewPoint": 6,
        "chancePrecipitation": 0,
        "chanceRain": 0,
        "chanceSnow": 0,
        "chanceThunder": 0,
        "chanceSleet": 0,
        "icon": "partly-cloudy-day",
        "day": "Tuesday",
        "dayShort": "Tue"
      },
      {
        "date": 1651662000,
        "maxTemp": 19,
        "minTemp": 9,
        "sunrise": "06:26",
        "sunset": "21:10",
        "summary": "scattered clouds",
        "windSpeed": 3.39,
        "windDir": 357,
        "percipitation": 0,
        "humidity": 39,
        "pressure": 1018,
        "cloudCover": 45,
        "dewPoint": 4,
        "chancePrecipitation": 0,
        "chanceRain": 0,
        "chanceSnow": 0,
        "chanceThunder": 0,
        "chanceSleet": 0,
        "icon": "cloudy",
        "day": "Wednesday",
        "dayShort": "Wed"
      },
      {
        "date": 1651748400,
        "maxTemp": 20,
        "minTemp": 10,
        "sunrise": "06:24",
        "sunset": "21:12",
        "summary": "overcast clouds",
        "windSpeed": 2.47,
        "windDir": 331,
        "percipitation": 0,
        "humidity": 45,
        "pressure": 1018,
        "cloudCover": 100,
        "dewPoint": 6,
        "chancePrecipitation": 0,
        "chanceRain": 0,
        "chanceSnow": 0,
        "chanceThunder": 0,
        "chanceSleet": 0,
        "icon": "cloudy",
        "day": "Thursday",
        "dayShort": "Thu"
      }
    ],
    "timezone": "Europe/Paris",
    "nextHours": [
      {
        "hour": "11:00",
        "temp": 15,
        "summary": "clear sky",
        "icon": "clear-day"
      },
      {
        "hour": "12:00",
        "temp": 16,
        "summary": "few clouds",
        "icon": "partly-cloudy-day"
      },
      {
        "hour": "13:00",
        "temp": 17,
        "summary": "scattered clouds",
        "icon": "cloudy"
      },
      {
        "hour": "14:00",
        "temp": 18,
        "summary": "scattered clouds",
        "icon": "cloudy"
      },
      {
        "hour": "15:00",
        "temp": 19,
        "summary": "few clouds",
        "icon": "partly-cloudy-day"
      },
      {
        "hour": "16:00",
        "temp": 21,
        "summary": "scattered clouds",
        "icon": "cloudy"
      },
      {
        "hour": "17:00",
        "temp": 21,
        "summary": "broken clouds",
        "icon": "cloudy"
      },
      {
        "hour": "18:00",
        "temp": 20,
        "summary": "broken clouds",
        "icon": "cloudy"
      },
      {
        "hour": "19:00",
        "temp": 20,
        "summary": "broken clouds",
        "icon": "cloudy"
      },
      {
        "hour": "20:00",
        "temp": 18,
        "summary": "broken clouds",
        "icon": "cloudy"
      },
      {
        "hour": "21:00",
        "temp": 16,
        "summary": "overcast clouds",
        "icon": "cloudy"
      },
      {
        "hour": "22:00",
        "temp": 15,
        "summary": "overcast clouds",
        "icon": "cloudy"
      },
      {
        "hour": "23:00",
        "temp": 14,
        "summary": "overcast clouds",
        "icon": "cloudy"
      },
      {
        "hour": "00:00",
        "temp": 14,
        "summary": "overcast clouds",
        "icon": "cloudy"
      },
      {
        "hour": "01:00",
        "temp": 13,
        "summary": "overcast clouds",
        "icon": "cloudy"
      },
      {
        "hour": "02:00",
        "temp": 12,
        "summary": "overcast clouds",
        "icon": "cloudy"
      },
      {
        "hour": "03:00",
        "temp": 11,
        "summary": "overcast clouds",
        "icon": "cloudy"
      },
      {
        "hour": "04:00",
        "temp": 11,
        "summary": "overcast clouds",
        "icon": "cloudy"
      },
      {
        "hour": "05:00",
        "temp": 10,
        "summary": "overcast clouds",
        "icon": "cloudy"
      },
      {
        "hour": "06:00",
        "temp": 10,
        "summary": "overcast clouds",
        "icon": "cloudy"
      },
      {
        "hour": "07:00",
        "temp": 10,
        "summary": "overcast clouds",
        "icon": "cloudy"
      },
      {
        "hour": "08:00",
        "temp": 11,
        "summary": "overcast clouds",
        "icon": "cloudy"
      },
      {
        "hour": "09:00",
        "temp": 12,
        "summary": "overcast clouds",
        "icon": "cloudy"
      },
      {
        "hour": "10:00",
        "temp": 13,
        "summary": "overcast clouds",
        "icon": "cloudy"
      }
    ]
  },
  {
    "source": "ow",
    "current": {
      "icon": "clear-day",
      "temp": 16,
      "summary": "clear sky",
      "windDir": 60,
      "humidity": 59,
      "pressure": 1026,
      "feelsLike": 15,
      "windSpeed": 5.66,
      "cloudCover": 0,
      "visibility": 10,
      "percipitation": 0
    },
    "forecast": [
      {
        "date": 1651143600,
        "maxTemp": 21,
        "minTemp": 9,
        "sunrise": "06:35",
        "sunset": "21:00",
        "summary": "scattered clouds",
        "windSpeed": 5.13,
        "windDir": 73,
        "percipitation": 0,
        "humidity": 50,
        "pressure": 1026,
        "cloudCover": 26,
        "dewPoint": 6,
        "chancePrecipitation": 0,
        "chanceRain": 0,
        "chanceSnow": 0,
        "chanceThunder": 0,
        "chanceSleet": 0,
        "icon": "cloudy",
        "day": "Thursday",
        "dayShort": "Thu"
      },
      {
        "date": 1651230000,
        "maxTemp": 18,
        "minTemp": 10,
        "sunrise": "06:33",
        "sunset": "21:01",
        "summary": "overcast clouds",
        "windSpeed": 4.45,
        "windDir": 19,
        "percipitation": 0,
        "humidity": 53,
        "pressure": 1028,
        "cloudCover": 100,
        "dewPoint": 6,
        "chancePrecipitation": 6,
        "chanceRain": 0,
        "chanceSnow": 0,
        "chanceThunder": 0,
        "chanceSleet": 0,
        "icon": "cloudy",
        "day": "Friday",
        "dayShort": "Fri"
      },
      {
        "date": 1651316400,
        "maxTemp": 17,
        "minTemp": 8,
        "sunrise": "06:32",
        "sunset": "21:03",
        "summary": "clear sky",
        "windSpeed": 4.39,
        "windDir": 19,
        "percipitation": 0,
        "humidity": 44,
        "pressure": 1026,
        "cloudCover": 1,
        "dewPoint": 3,
        "chancePrecipitation": 0,
        "chanceRain": 0,
        "chanceSnow": 0,
        "chanceThunder": 0,
        "chanceSleet": 0,
        "icon": "clear-day",
        "day": "Saturday",
        "dayShort": "Sat"
      },
      {
        "date": 1651402800,
        "maxTemp": 18,
        "minTemp": 9,
        "sunrise": "06:30",
        "sunset": "21:04",
        "summary": "overcast clouds",
        "windSpeed": 2.56,
        "windDir": 20,
        "percipitation": 0,
        "humidity": 37,
        "pressure": 1022,
        "cloudCover": 100,
        "dewPoint": 2,
        "chancePrecipitation": 0,
        "chanceRain": 0,
        "chanceSnow": 0,
        "chanceThunder": 0,
        "chanceSleet": 0,
        "icon": "cloudy",
        "day": "Sunday",
        "dayShort": "Sun"
      },
      {
        "date": 1651489200,
        "maxTemp": 19,
        "minTemp": 10,
        "sunrise": "06:28",
        "sunset": "21:06",
        "summary": "light rain",
        "windSpeed": 4.24,
        "windDir": 39,
        "percipitation": 0.23,
        "humidity": 47,
        "pressure": 1018,
        "cloudCover": 100,
        "dewPoint": 7,
        "chancePrecipitation": 27,
        "chanceRain": 0,
        "chanceSnow": 0,
        "chanceThunder": 0,
        "chanceSleet": 0,
        "icon": "rain",
        "day": "Monday",
        "dayShort": "Mon"
      },
      {
        "date": 1651575600,
        "maxTemp": 20,
        "minTemp": 9,
        "sunrise": "06:27",
        "sunset": "21:07",
        "summary": "clear sky",
        "windSpeed": 4.51,
        "windDir": 42,
        "percipitation": 0,
        "humidity": 42,
        "pressure": 1017,
        "cloudCover": 9,
        "dewPoint": 6,
        "chancePrecipitation": 0,
        "chanceRain": 0,
        "chanceSnow": 0,
        "chanceThunder": 0,
        "chanceSleet": 0,
        "icon": "clear-day",
        "day": "Tuesday",
        "dayShort": "Tue"
      },
      {
        "date": 1651662000,
        "maxTemp": 20,
        "minTemp": 9,
        "sunrise": "06:25",
        "sunset": "21:09",
        "summary": "scattered clouds",
        "windSpeed": 3.49,
        "windDir": 24,
        "percipitation": 0,
        "humidity": 38,
        "pressure": 1018,
        "cloudCover": 50,
        "dewPoint": 4,
        "chancePrecipitation": 0,
        "chanceRain": 0,
        "chanceSnow": 0,
        "chanceThunder": 0,
        "chanceSleet": 0,
        "icon": "cloudy",
        "day": "Wednesday",
        "dayShort": "Wed"
      },
      {
        "date": 1651748400,
        "maxTemp": 20,
        "minTemp": 11,
        "sunrise": "06:23",
        "sunset": "21:10",
        "summary": "overcast clouds",
        "windSpeed": 2.92,
        "windDir": 355,
        "percipitation": 0,
        "humidity": 41,
        "pressure": 1018,
        "cloudCover": 100,
        "dewPoint": 5,
        "chancePrecipitation": 0,
        "chanceRain": 0,
        "chanceSnow": 0,
        "chanceThunder": 0,
        "chanceSleet": 0,
        "icon": "cloudy",
        "day": "Thursday",
        "dayShort": "Thu"
      }
    ],
    "timezone": "Europe/Paris",
    "nextHours": [
      {
        "hour": "11:00",
        "temp": 16,
        "summary": "clear sky",
        "icon": "clear-day"
      },
      {
        "hour": "12:00",
        "temp": 16,
        "summary": "few clouds",
        "icon": "partly-cloudy-day"
      },
      {
        "hour": "13:00",
        "temp": 17,
        "summary": "scattered clouds",
        "icon": "cloudy"
      },
      {
        "hour": "14:00",
        "temp": 18,
        "summary": "scattered clouds",
        "icon": "cloudy"
      },
      {
        "hour": "15:00",
        "temp": 19,
        "summary": "broken clouds",
        "icon": "cloudy"
      },
      {
        "hour": "16:00",
        "temp": 21,
        "summary": "overcast clouds",
        "icon": "cloudy"
      },
      {
        "hour": "17:00",
        "temp": 21,
        "summary": "overcast clouds",
        "icon": "cloudy"
      },
      {
        "hour": "18:00",
        "temp": 20,
        "summary": "broken clouds",
        "icon": "cloudy"
      },
      {
        "hour": "19:00",
        "temp": 20,
        "summary": "broken clouds",
        "icon": "cloudy"
      },
      {
        "hour": "20:00",
        "temp": 18,
        "summary": "broken clouds",
        "icon": "cloudy"
      },
      {
        "hour": "21:00",
        "temp": 16,
        "summary": "broken clouds",
        "icon": "cloudy"
      },
      {
        "hour": "22:00",
        "temp": 15,
        "summary": "broken clouds",
        "icon": "cloudy"
      },
      {
        "hour": "23:00",
        "temp": 14,
        "summary": "broken clouds",
        "icon": "cloudy"
      },
      {
        "hour": "00:00",
        "temp": 14,
        "summary": "overcast clouds",
        "icon": "cloudy"
      },
      {
        "hour": "01:00",
        "temp": 13,
        "summary": "overcast clouds",
        "icon": "cloudy"
      },
      {
        "hour": "02:00",
        "temp": 12,
        "summary": "overcast clouds",
        "icon": "cloudy"
      },
      {
        "hour": "03:00",
        "temp": 11,
        "summary": "overcast clouds",
        "icon": "cloudy"
      },
      {
        "hour": "04:00",
        "temp": 11,
        "summary": "overcast clouds",
        "icon": "cloudy"
      },
      {
        "hour": "05:00",
        "temp": 11,
        "summary": "overcast clouds",
        "icon": "cloudy"
      },
      {
        "hour": "06:00",
        "temp": 10,
        "summary": "overcast clouds",
        "icon": "cloudy"
      },
      {
        "hour": "07:00",
        "temp": 10,
        "summary": "overcast clouds",
        "icon": "cloudy"
      },
      {
        "hour": "08:00",
        "temp": 11,
        "summary": "overcast clouds",
        "icon": "cloudy"
      },
      {
        "hour": "09:00",
        "temp": 12,
        "summary": "overcast clouds",
        "icon": "cloudy"
      },
      {
        "hour": "10:00",
        "temp": 13,
        "summary": "overcast clouds",
        "icon": "cloudy"
      }
    ]
  },
  {
    "source": "ow",
    "current": {
      "icon": "cloudy",
      "temp": 11,
      "summary": "overcast clouds",
      "windDir": 64,
      "humidity": 76,
      "pressure": 1028,
      "feelsLike": 10,
      "windSpeed": 8.47,
      "cloudCover": 100,
      "visibility": 10,
      "percipitation": 0
    },
    "forecast": [
      {
        "date": 1651147200,
        "maxTemp": 14,
        "minTemp": 9,
        "sunrise": "06:50",
        "sunset": "21:18",
        "summary": "overcast clouds",
        "windSpeed": 9.54,
        "windDir": 64,
        "percipitation": 0,
        "humidity": 73,
        "pressure": 1028,
        "cloudCover": 100,
        "dewPoint": 8,
        "chancePrecipitation": 0,
        "chanceRain": 0,
        "chanceSnow": 0,
        "chanceThunder": 0,
        "chanceSleet": 0,
        "icon": "cloudy",
        "day": "Thursday",
        "dayShort": "Thu"
      },
      {
        "date": 1651233600,
        "maxTemp": 14,
        "minTemp": 8,
        "sunrise": "06:48",
        "sunset": "21:19",
        "summary": "overcast clouds",
        "windSpeed": 6.65,
        "windDir": 57,
        "percipitation": 0,
        "humidity": 68,
        "pressure": 1030,
        "cloudCover": 99,
        "dewPoint": 8,
        "chancePrecipitation": 0,
        "chanceRain": 0,
        "chanceSnow": 0,
        "chanceThunder": 0,
        "chanceSleet": 0,
        "icon": "cloudy",
        "day": "Friday",
        "dayShort": "Fri"
      },
      {
        "date": 1651320000,
        "maxTemp": 13,
        "minTemp": 7,
        "sunrise": "06:47",
        "sunset": "21:21",
        "summary": "few clouds",
        "windSpeed": 5.75,
        "windDir": 61,
        "percipitation": 0,
        "humidity": 65,
        "pressure": 1028,
        "cloudCover": 12,
        "dewPoint": 7,
        "chancePrecipitation": 0,
        "chanceRain": 0,
        "chanceSnow": 0,
        "chanceThunder": 0,
        "chanceSleet": 0,
        "icon": "partly-cloudy-day",
        "day": "Saturday",
        "dayShort": "Sat"
      },
      {
        "date": 1651406400,
        "maxTemp": 13,
        "minTemp": 9,
        "sunrise": "06:45",
        "sunset": "21:22",
        "summary": "overcast clouds",
        "windSpeed": 4,
        "windDir": 45,
        "percipitation": 0,
        "humidity": 66,
        "pressure": 1023,
        "cloudCover": 100,
        "dewPoint": 7,
        "chancePrecipitation": 0,
        "chanceRain": 0,
        "chanceSnow": 0,
        "chanceThunder": 0,
        "chanceSleet": 0,
        "icon": "cloudy",
        "day": "Sunday",
        "dayShort": "Sun"
      },
      {
        "date": 1651492800,
        "maxTemp": 14,
        "minTemp": 9,
        "sunrise": "06:43",
        "sunset": "21:24",
        "summary": "overcast clouds",
        "windSpeed": 6.95,
        "windDir": 59,
        "percipitation": 0,
        "humidity": 64,
        "pressure": 1021,
        "cloudCover": 100,
        "dewPoint": 8,
        "chancePrecipitation": 0,
        "chanceRain": 0,
        "chanceSnow": 0,
        "chanceThunder": 0,
        "chanceSleet": 0,
        "icon": "cloudy",
        "day": "Monday",
        "dayShort": "Mon"
      },
      {
        "date": 1651579200,
        "maxTemp": 14,
        "minTemp": 9,
        "sunrise": "06:41",
        "sunset": "21:25",
        "summary": "broken clouds",
        "windSpeed": 6.56,
        "windDir": 52,
        "percipitation": 0,
        "humidity": 62,
        "pressure": 1021,
        "cloudCover": 74,
        "dewPoint": 7,
        "chancePrecipitation": 0,
        "chanceRain": 0,
        "chanceSnow": 0,
        "chanceThunder": 0,
        "chanceSleet": 0,
        "icon": "cloudy",
        "day": "Tuesday",
        "dayShort": "Tue"
      },
      {
        "date": 1651665600,
        "maxTemp": 14,
        "minTemp": 9,
        "sunrise": "06:40",
        "sunset": "21:27",
        "summary": "few clouds",
        "windSpeed": 5.04,
        "windDir": 316,
        "percipitation": 0,
        "humidity": 69,
        "pressure": 1020,
        "cloudCover": 23,
        "dewPoint": 8,
        "chancePrecipitation": 0,
        "chanceRain": 0,
        "chanceSnow": 0,
        "chanceThunder": 0,
        "chanceSleet": 0,
        "icon": "partly-cloudy-day",
        "day": "Wednesday",
        "dayShort": "Wed"
      },
      {
        "date": 1651752000,
        "maxTemp": 13,
        "minTemp": 12,
        "sunrise": "06:38",
        "sunset": "21:28",
        "summary": "broken clouds",
        "windSpeed": 4.59,
        "windDir": 305,
        "percipitation": 0,
        "humidity": 87,
        "pressure": 1019,
        "cloudCover": 62,
        "dewPoint": 11,
        "chancePrecipitation": 0,
        "chanceRain": 0,
        "chanceSnow": 0,
        "chanceThunder": 0,
        "chanceSleet": 0,
        "icon": "cloudy",
        "day": "Thursday",
        "dayShort": "Thu"
      }
    ],
    "timezone": "Europe/Paris",
    "nextHours": [
      {
        "hour": "11:00",
        "temp": 11,
        "summary": "overcast clouds",
        "icon": "cloudy"
      },
      {
        "hour": "12:00",
        "temp": 11,
        "summary": "overcast clouds",
        "icon": "cloudy"
      },
      {
        "hour": "13:00",
        "temp": 12,
        "summary": "overcast clouds",
        "icon": "cloudy"
      },
      {
        "hour": "14:00",
        "temp": 13,
        "summary": "overcast clouds",
        "icon": "cloudy"
      },
      {
        "hour": "15:00",
        "temp": 13,
        "summary": "overcast clouds",
        "icon": "cloudy"
      },
      {
        "hour": "16:00",
        "temp": 14,
        "summary": "overcast clouds",
        "icon": "cloudy"
      },
      {
        "hour": "17:00",
        "temp": 14,
        "summary": "overcast clouds",
        "icon": "cloudy"
      },
      {
        "hour": "18:00",
        "temp": 13,
        "summary": "overcast clouds",
        "icon": "cloudy"
      },
      {
        "hour": "19:00",
        "temp": 13,
        "summary": "overcast clouds",
        "icon": "cloudy"
      },
      {
        "hour": "20:00",
        "temp": 12,
        "summary": "overcast clouds",
        "icon": "cloudy"
      },
      {
        "hour": "21:00",
        "temp": 11,
        "summary": "broken clouds",
        "icon": "cloudy"
      },
      {
        "hour": "22:00",
        "temp": 10,
        "summary": "broken clouds",
        "icon": "cloudy"
      },
      {
        "hour": "23:00",
        "temp": 9,
        "summary": "broken clouds",
        "icon": "cloudy"
      },
      {
        "hour": "00:00",
        "temp": 9,
        "summary": "broken clouds",
        "icon": "cloudy"
      },
      {
        "hour": "01:00",
        "temp": 9,
        "summary": "broken clouds",
        "icon": "cloudy"
      },
      {
        "hour": "02:00",
        "temp": 10,
        "summary": "overcast clouds",
        "icon": "cloudy"
      },
      {
        "hour": "03:00",
        "temp": 10,
        "summary": "overcast clouds",
        "icon": "cloudy"
      },
      {
        "hour": "04:00",
        "temp": 9,
        "summary": "overcast clouds",
        "icon": "cloudy"
      },
      {
        "hour": "05:00",
        "temp": 9,
        "summary": "overcast clouds",
        "icon": "cloudy"
      },
      {
        "hour": "06:00",
        "temp": 10,
        "summary": "overcast clouds",
        "icon": "cloudy"
      },
      {
        "hour": "07:00",
        "temp": 9,
        "summary": "overcast clouds",
        "icon": "cloudy"
      },
      {
        "hour": "08:00",
        "temp": 10,
        "summary": "overcast clouds",
        "icon": "cloudy"
      },
      {
        "hour": "09:00",
        "temp": 11,
        "summary": "overcast clouds",
        "icon": "cloudy"
      },
      {
        "hour": "10:00",
        "temp": 12,
        "summary": "overcast clouds",
        "icon": "cloudy"
      }
    ]
  }
]