[
  {
    "source": "ow",
    "current": {
      "icon": "clear-day",
      "temp": 9,
      "summary": "clear sky",
      "windDir": 20,
      "humidity": 76,
      "pressure": 1034,
      "feelsLike": 8,
      "windSpeed": 2.06,
      "cloudCover": 0,
      "visibility": 10,
      "percipitation": 0
    },
    "forecast": [
      {
        "date": 1647518400,
        "maxTemp": 12,
        "minTemp": 7,
        "sunrise": "07:01",
        "sunset": "18:59",
        "summary": "overcast clouds",
        "windSpeed": 4.97,
        "windDir": 326,
        "percipitation": 0,
        "humidity": 43,
        "pressure": 1032,
        "cloudCover": 95,
        "dewPoint": 0,
        "chancePrecipitation": 13,
        "chanceRain": 0,
        "chanceSnow": 0,
        "chanceThunder": 0,
        "chanceSleet": 0,
        "icon": "cloudy",
        "day": "Thursday",
        "dayShort": "Thu"
      },
      {
        "date": 1647601200,
        "maxTemp": 15,
        "minTemp": 5,
        "sunrise": "06:59",
        "sunset": "19:00",
        "summary": "clear sky",
        "windSpeed": 7.27,
        "windDir": 61,
        "percipitation": 0,
        "humidity": 28,
        "pressure": 1038,
        "cloudCover": 3,
        "dewPoint": -6,
        "chancePrecipitation": 0,
        "chanceRain": 0,
        "chanceSnow": 0,
        "chanceThunder": 0,
        "chanceSleet": 0,
        "icon": "clear-day",
        "day": "Friday",
        "dayShort": "Fri"
      },
      {
        "date": 1647687600,
        "maxTemp": 15,
        "minTemp": 6,
        "sunrise": "06:57",
        "sunset": "19:02",
        "summary": "clear sky",
        "windSpeed": 6.81,
        "windDir": 79,
        "percipitation": 0,
        "humidity": 42,
        "pressure": 1033,
        "cloudCover": 0,
        "dewPoint": 0,
        "chancePrecipitation": 0,
        "chanceRain": 0,
        "chanceSnow": 0,
        "chanceThunder": 0,
        "chanceSleet": 0,
        "icon": "clear-day",
        "day": "Saturday",
        "dayShort": "Sat"
      },
      {
        "date": 1647774000,
        "maxTemp": 11,
        "minTemp": 3,
        "sunrise": "06:55",
        "sunset": "19:03",
        "summary": "light rain",
        "windSpeed": 4.09,
        "windDir": 53,
        "percipitation": 0.57,
        "humidity": 42,
        "pressure": 1023,
        "cloudCover": 15,
        "dewPoint": -2,
        "chancePrecipitation": 26,
        "chanceRain": 0,
        "chanceSnow": 0,
        "chanceThunder": 0,
        "chanceSleet": 0,
        "icon": "rain",
        "day": "Sunday",
        "dayShort": "Sun"
      },
      {
        "date": 1647860400,
        "maxTemp": 17,
        "minTemp": 8,
        "sunrise": "06:52",
        "sunset": "19:05",
        "summary": "light rain",
        "windSpeed": 3.65,
        "windDir": 164,
        "percipitation": 2.24,
        "humidity": 55,
        "pressure": 1028,
        "cloudCover": 52,
        "dewPoint": 6,
        "chancePrecipitation": 61,
        "chanceRain": 0,
        "chanceSnow": 0,
        "chanceThunder": 0,
        "chanceSleet": 0,
        "icon": "rain",
        "day": "Monday",
        "dayShort": "Mon"
      },
      {
        "date": 1647946800,
        "maxTemp": 18,
        "minTemp": 8,
        "sunrise": "06:50",
        "sunset": "19:06",
        "summary": "clear sky",
        "windSpeed": 3.33,
        "windDir": 95,
        "percipitation": 0,
        "humidity": 41,
        "pressure": 1027,
        "cloudCover": 3,
        "dewPoint": 3,
        "chancePrecipitation": 0,
        "chanceRain": 0,
        "chanceSnow": 0,
        "chanceThunder": 0,
        "chanceSleet": 0,
        "icon": "clear-day",
        "day": "Tuesday",
        "dayShort": "Tue"
      },
      {
        "date": 1648033200,
        "maxTemp": 18,
        "minTemp": 9,
        "sunrise": "06:48",
        "sunset": "19:08",
        "summary": "clear sky",
        "windSpeed": 2.93,
        "windDir": 138,
        "percipitation": 0,
        "humidity": 24,
        "pressure": 1025,
        "cloudCover": 0,
        "dewPoint": -4,
        "chancePrecipitation": 0,
        "chanceRain": 0,
        "chanceSnow": 0,
        "chanceThunder": 0,
        "chanceSleet": 0,
        "icon": "clear-day",
        "day": "Wednesday",
        "dayShort": "Wed"
      },
      {
        "date": 1648119600,
        "maxTemp": 19,
        "minTemp": 9,
        "sunrise": "06:46",
        "sunset": "19:09",
        "summary": "clear sky",
        "windSpeed": 2.36,
        "windDir": 149,
        "percipitation": 0,
        "humidity": 34,
        "pressure": 1026,
        "cloudCover": 0,
        "dewPoint": 1,
        "chancePrecipitation": 0,
        "chanceRain": 0,
        "chanceSnow": 0,
        "chanceThunder": 0,
        "chanceSleet": 0,
        "icon": "clear-day",
        "day": "Thursday",
        "dayShort": "Thu"
      }
    ],
    "timezone": "Europe/Paris",
    "nextHours": [
      {
        "hour": "18:00",
        "temp": 9,
        "summary": "clear sky",
        "icon": "clear-day"
      },
      {
        "hour": "19:00",
        "temp": 9,
        "summary": "few clouds",
        "icon": "partly-cloudy-night"
      },
      {
        "hour": "20:00",
        "temp": 9,
        "summary": "scattered clouds",
        "icon": "cloudy"
      },
      {
        "hour": "21:00",
        "temp": 9,
        "summary": "scattered clouds",
        "icon": "cloudy"
      },
      {
        "hour": "22:00",
        "temp": 8,
        "summary": "scattered clouds",
        "icon": "cloudy"
      },
      {
        "hour": "23:00",
        "temp": 8,
        "summary": "scattered clouds",
        "icon": "cloudy"
      },
      {
        "hour": "00:00",
        "temp": 7,
        "summary": "few clouds",
        "icon": "partly-cloudy-night"
      },
      {
        "hour": "01:00",
        "temp": 7,
        "summary": "few clouds",
        "icon": "partly-cloudy-night"
      },
      {
        "hour": "02:00",
        "temp": 7,
        "summary": "clear sky",
        "icon": "clear-night"
      },
      {
        "hour": "03:00",
        "temp": 6,
        "summary": "clear sky",
        "icon": "clear-night"
      },
      {
        "hour": "04:00",
        "temp": 6,
        "summary": "clear sky",
        "icon": "clear-night"
      },
      {
        "hour": "05:00",
        "temp": 6,
        "summary": "clear sky",
        "icon": "clear-night"
      },
      {
        "hour": "06:00",
        "temp": 5,
        "summary": "clear sky",
        "icon": "clear-night"
      },
      {
        "hour": "07:00",
        "temp": 5,
        "summary": "clear sky",
        "icon": "clear-day"
      },
      {
        "hour": "08:00",
        "temp": 6,
        "summary": "clear sky",
        "icon": "clear-day"
      },
      {
        "hour": "09:00",
        "temp": 7,
        "summary": "clear sky",
        "icon": "clear-day"
      },
      {
        "hour": "10:00",
        "temp": 9,
        "summary": "clear sky",
        "icon": "clear-day"
      },
      {
        "hour": "11:00",
        "temp": 11,
        "summary": "clear sky",
        "icon": "clear-day"
      },
      {
        "hour": "12:00",
        "temp": 12,
        "summary": "clear sky",
        "icon": "clear-day"
      },
      {
        "hour": "13:00",
        "temp": 14,
        "summary": "clear sky",
        "icon": "clear-day"
      },
      {
        "hour": "14:00",
        "temp": 14,
        "summary": "clear sky",
        "icon": "clear-day"
      },
      {
        "hour": "15:00",
        "temp": 15,
        "summary": "clear sky",
        "icon": "clear-day"
      },
      {
        "hour": "16:00",
        "temp": 15,
        "summary": "clear sky",
        "icon": "clear-day"
      },
      {
        "hour": "17:00",
        "temp": 15,
        "summary": "clear sky",
        "icon": "clear-day"
      }
    ]
  },
  {
    "source": "ow",
    "current": {
      "icon": "partly-cloudy-day",
      "temp": 9,
      "summary": "few clouds",
      "windDir": 10,
      "humidity": 68,
      "pressure": 1033,
      "feelsLike": 6,
      "windSpeed": 5.66,
      "cloudCover": 20,
      "visibility": 10,
      "percipitation": 0
    },
    "forecast": [
      {
        "date": 1647514800,
        "maxTemp": 12,
        "minTemp": 8,
        "sunrise": "07:00",
        "sunset": "18:57",
        "summary": "overcast clouds",
        "windSpeed": 4.78,
        "windDir": 13,
        "percipitation": 0,
        "humidity": 47,
        "pressure": 1032,
        "cloudCover": 100,
        "dewPoint": 0,
        "chancePrecipitation": 16,
        "chanceRain": 0,
        "chanceSnow": 0,
        "chanceThunder": 0,
        "chanceSleet": 0,
        "icon": "cloudy",
        "day": "Thursday",
        "dayShort": "Thu"
      },
      {
        "date": 1647601200,
        "maxTemp": 15,
        "minTemp": 5,
        "sunrise": "06:58",
        "sunset": "18:59",
        "summary": "clear sky",
        "windSpeed": 7.02,
        "windDir": 59,
        "percipitation": 0,
        "humidity": 28,
        "pressure": 1038,
        "cloudCover": 3,
        "dewPoint": -6,
        "chancePrecipitation": 0,
        "chanceRain": 0,
        "chanceSnow": 0,
        "chanceThunder": 0,
        "chanceSleet": 0,
        "icon": "clear-day",
        "day": "Friday",
        "dayShort": "Fri"
      },
      {
        "date": 1647687600,
        "maxTemp": 15,
        "minTemp": 6,
        "sunrise": "06:56",
        "sunset": "19:00",
        "summary": "clear sky",
        "windSpeed": 6.64,
        "windDir": 77,
        "percipitation": 0,
        "humidity": 42,
        "pressure": 1033,
        "cloudCover": 0,
        "dewPoint": 0,
        "chancePrecipitation": 0,
        "chanceRain": 0,
        "chanceSnow": 0,
        "chanceThunder": 0,
        "chanceSleet": 0,
        "icon": "clear-day",
        "day": "Saturday",
        "dayShort": "Sat"
      },
      {
        "date": 1647774000,
        "maxTemp": 10,
        "minTemp": 3,
        "sunrise": "06:53",
        "sunset": "19:02",
        "summary": "light rain",
        "windSpeed": 4.09,
        "windDir": 59,
        "percipitation": 1.26,
        "humidity": 44,
        "pressure": 1023,
        "cloudCover": 37,
        "dewPoint": -2,
        "chancePrecipitation": 40,
        "chanceRain": 0,
        "chanceSnow": 0,
        "chanceThunder": 0,
        "chanceSleet": 0,
        "icon": "rain",
        "day": "Sunday",
        "dayShort": "Sun"
      },
      {
        "date": 1647860400,
        "maxTemp": 17,
        "minTemp": 8,
        "sunrise": "06:51",
        "sunset": "19:03",
        "summary": "light rain",
        "windSpeed": 3.37,
        "windDir": 156,
        "percipitation": 1.46,
        "humidity": 54,
        "pressure": 1028,
        "cloudCover": 40,
        "dewPoint": 6,
        "chancePrecipitation": 71,
        "chanceRain": 0,
        "chanceSnow": 0,
        "chanceThunder": 0,
        "chanceSleet": 0,
        "icon": "rain",
        "day": "Monday",
        "dayShort": "Mon"
      },
      {
        "date": 1647946800,
        "maxTemp": 18,
        "minTemp": 8,
        "sunrise": "06:49",
        "sunset": "19:05",
        "summary": "clear sky",
        "windSpeed": 3.34,
        "windDir": 96,
        "percipitation": 0,
        "humidity": 44,
        "pressure": 1027,
        "cloudCover": 2,
        "dewPoint": 4,
        "chancePrecipitation": 0,
        "chanceRain": 0,
        "chanceSnow": 0,
        "chanceThunder": 0,
        "chanceSleet": 0,
        "icon": "clear-day",
        "day": "Tuesday",
        "dayShort": "Tue"
      },
      {
        "date": 1648033200,
        "maxTemp": 18,
        "minTemp": 8,
        "sunrise": "06:47",
        "sunset": "19:06",
        "summary": "clear sky",
        "windSpeed": 3.03,
        "windDir": 155,
        "percipitation": 0,
        "humidity": 25,
        "pressure": 1025,
        "cloudCover": 0,
        "dewPoint": -4,
        "chancePrecipitation": 0,
        "chanceRain": 0,
        "chanceSnow": 0,
        "chanceThunder": 0,
        "chanceSleet": 0,
        "icon": "clear-day",
        "day": "Wednesday",
        "dayShort": "Wed"
      },
      {
        "date": 1648119600,
        "maxTemp": 18,
        "minTemp": 8,
        "sunrise": "06:45",
        "sunset": "19:08",
        "summary": "clear sky",
        "windSpeed": 2.66,
        "windDir": 122,
        "percipitation": 0,
        "humidity": 35,
        "pressure": 1026,
        "cloudCover": 0,
        "dewPoint": 1,
        "chancePrecipitation": 0,
        "chanceRain": 0,
        "chanceSnow": 0,
        "chanceThunder": 0,
        "chanceSleet": 0,
        "icon": "clear-day",
        "day": "Thursday",
        "dayShort": "Thu"
      }
    ],
    "timezone": "Europe/Paris",
    "nextHours": [
      {
        "hour": "17:00",
        "temp": 10,
        "summary": "scattered clouds",
        "icon": "cloudy"
      },
      {
        "hour": "18:00",
        "temp": 9,
        "summary": "few clouds",
        "icon": "partly-cloudy-day"
      },
      {
        "hour": "19:00",
        "temp": 9,
        "summary": "scattered clouds",
        "icon": "cloudy"
      },
      {
        "hour": "20:00",
        "temp": 10,
        "summary": "broken clouds",
        "icon": "cloudy"
      },
      {
        "hour": "21:00",
        "temp": 9,
        "summary": "broken clouds",
        "icon": "cloudy"
      },
      {
        "hour": "22:00",
        "temp": 9,
        "summary": "broken clouds",
        "icon": "cloudy"
      },
      {
        "hour": "23:00",
        "temp": 8,
        "summary": "broken clouds",
        "icon": "cloudy"
      },
      {
        "hour": "00:00",
        "temp": 8,
        "summary": "scattered clouds",
        "icon": "cloudy"
      },
      {
        "hour": "01:00",
        "temp": 7,
        "summary": "scattered clouds",
        "icon": "cloudy"
      },
      {
        "hour": "02:00",
        "temp": 7,
        "summary": "clear sky",
        "icon": "clear-night"
      },
      {
        "hour": "03:00",
        "temp": 6,
        "summary": "clear sky",
        "icon": "clear-night"
      },
      {
        "hour": "04:00",
        "temp": 6,
        "summary": "clear sky",
        "icon": "clear-night"
      },
      {
        "hour": "05:00",
        "temp": 6,
        "summary": "clear sky",
        "icon": "clear-night"
      },
      {
        "hour": "06:00",
        "temp": 6,
        "summary": "clear sky",
        "icon": "clear-night"
      },
      {
        "hour": "07:00",
        "temp": 5,
        "summary": "clear sky",
        "icon": "clear-day"
      },
      {
        "hour": "08:00",
        "temp": 6,
        "summary": "clear sky",
        "icon": "clear-day"
      },
      {
        "hour": "09:00",
        "temp": 7,
        "summary": "clear sky",
        "icon": "clear-day"
      },
      {
        "hour": "10:00",
        "temp": 9,
        "summary": "clear sky",
        "icon": "clear-day"
      },
      {
        "hour": "11:00",
        "temp": 11,
        "summary": "clear sky",
        "icon": "clear-day"
      },
      {
        "hour": "12:00",
        "temp": 12,
        "summary": "clear sky",
        "icon": "clear-day"
      },
      {
        "hour": "13:00",
        "temp": 13,
        "summary": "clear sky",
        "icon": "clear-day"
      },
      {
        "hour": "14:00",
        "temp": 14,
        "summary": "clear sky",
        "icon": "clear-day"
      },
      {
        "hour": "15:00",
        "temp": 15,
        "summary": "clear sky",
        "icon": "clear-day"
      },
      {
        "hour": "16:00",
        "temp": 15,
        "summary": "clear sky",
        "icon": "clear-day"
      }
    ]
  },
  {
    "source": "ow",
    "current": {
      "icon": "clear-day",
      "temp": 11,
      "summary": "clear sky",
      "windDir": 316,
      "humidity": 77,
      "pressure": 1035,
      "feelsLike": 10,
      "windSpeed": 3.58,
      "cloudCover": 5,
      "visibility": 10,
      "percipitation": 0
    },
    "forecast": [
      {
        "date": 1647518400,
        "maxTemp": 11,
        "minTemp": 6,
        "sunrise": "07:16",
        "sunset": "19:14",
        "summary": "clear sky",
        "windSpeed": 8.86,
        "windDir": 335,
        "percipitation": 0,
        "humidity": 65,
        "pressure": 1035,
        "cloudCover": 1,
        "dewPoint": 3,
        "chancePrecipitation": 2,
        "chanceRain": 0,
        "chanceSnow": 0,
        "chanceThunder": 0,
        "chanceSleet": 0,
        "icon": "clear-day",
        "day": "Thursday",
        "dayShort": "Thu"
      },
      {
        "date": 1647604800,
        "maxTemp": 12,
        "minTemp": 7,
        "sunrise": "07:14",
        "sunset": "19:15",
        "summary": "clear sky",
        "windSpeed": 10.39,
        "windDir": 78,
        "percipitation": 0,
        "humidity": 67,
        "pressure": 1039,
        "cloudCover": 0,
        "dewPoint": 6,
        "chancePrecipitation": 0,
        "chanceRain": 0,
        "chanceSnow": 0,
        "chanceThunder": 0,
        "chanceSleet": 0,
        "icon": "clear-day",
        "day": "Friday",
        "dayShort": "Fri"
      },
      {
        "date": 1647691200,
        "maxTemp": 12,
        "minTemp": 7,
        "sunrise": "07:12",
        "sunset": "19:17",
        "summary": "clear sky",
        "windSpeed": 10.32,
        "windDir": 83,
        "percipitation": 0,
        "humidity": 64,
        "pressure": 1032,
        "cloudCover": 0,
        "dewPoint": 4,
        "chancePrecipitation": 0,
        "chanceRain": 0,
        "chanceSnow": 0,
        "chanceThunder": 0,
        "chanceSleet": 0,
        "icon": "clear-day",
        "day": "Saturday",
        "dayShort": "Sat"
      },
      {
        "date": 1647777600,
        "maxTemp": 9,
        "minTemp": 5,
        "sunrise": "07:10",
        "sunset": "19:18",
        "summary": "clear sky",
        "windSpeed": 8.08,
        "windDir": 78,
        "percipitation": 0,
        "humidity": 62,
        "pressure": 1024,
        "cloudCover": 2,
        "dewPoint": 2,
        "chancePrecipitation": 0,
        "chanceRain": 0,
        "chanceSnow": 0,
        "chanceThunder": 0,
        "chanceSleet": 0,
        "icon": "clear-day",
        "day": "Sunday",
        "dayShort": "Sun"
      },
      {
        "date": 1647864000,
        "maxTemp": 13,
        "minTemp": 5,
        "sunrise": "07:08",
        "sunset": "19:20",
        "summary": "light rain",
        "windSpeed": 6.15,
        "windDir": 168,
        "percipitation": 2.53,
        "humidity": 82,
        "pressure": 1025,
        "cloudCover": 72,
        "dewPoint": 9,
        "chancePrecipitation": 54,
        "chanceRain": 0,
        "chanceSnow": 0,
        "chanceThunder": 0,
        "chanceSleet": 0,
        "icon": "rain",
        "day": "Monday",
        "dayShort": "Mon"
      },
      {
        "date": 1647950400,
        "maxTemp": 13,
        "minTemp": 8,
        "sunrise": "07:05",
        "sunset": "19:21",
        "summary": "few clouds",
        "windSpeed": 5.19,
        "windDir": 136,
        "percipitation": 0,
        "humidity": 72,
        "pressure": 1025,
        "cloudCover": 17,
        "dewPoint": 8,
        "chancePrecipitation": 38,
        "chanceRain": 0,
        "chanceSnow": 0,
        "chanceThunder": 0,
        "chanceSleet": 0,
        "icon": "partly-cloudy-day",
        "day": "Tuesday",
        "dayShort": "Tue"
      },
      {
        "date": 1648036800,
        "maxTemp": 14,
        "minTemp": 8,
        "sunrise": "07:03",
        "sunset": "19:23",
        "summary": "clear sky",
        "windSpeed": 5.04,
        "windDir": 94,
        "percipitation": 0,
        "humidity": 66,
        "pressure": 1024,
        "cloudCover": 0,
        "dewPoint": 7,
        "chancePrecipitation": 0,
        "chanceRain": 0,
        "chanceSnow": 0,
        "chanceThunder": 0,
        "chanceSleet": 0,
        "icon": "clear-day",
        "day": "Wednesday",
        "dayShort": "Wed"
      },
      {
        "date": 1648123200,
        "maxTemp": 13,
        "minTemp": 8,
        "sunrise": "07:01",
        "sunset": "19:24",
        "summary": "clear sky",
        "windSpeed": 4.13,
        "windDir": 66,
        "percipitation": 0,
        "humidity": 62,
        "pressure": 1025,
        "cloudCover": 0,
        "dewPoint": 5,
        "chancePrecipitation": 0,
        "chanceRain": 0,
        "chanceSnow": 0,
        "chanceThunder": 0,
        "chanceSleet": 0,
        "icon": "clear-day",
        "day": "Thursday",
        "dayShort": "Thu"
      }
    ],
    "timezone": "Europe/Paris",
    "nextHours": [
      {
        "hour": "18:00",
        "temp": 11,
        "summary": "clear sky",
        "icon": "clear-day"
      },
      {
        "hour": "19:00",
        "temp": 11,
        "summary": "clear sky",
        "icon": "clear-day"
      },
      {
        "hour": "20:00",
        "temp": 10,
        "summary": "clear sky",
        "icon": "clear-night"
      },
      {
        "hour": "21:00",
        "temp": 9,
        "summary": "clear sky",
        "icon": "clear-night"
      },
      {
        "hour": "22:00",
        "temp": 9,
        "summary": "clear sky",
        "icon": "clear-night"
      },
      {
        "hour": "23:00",
        "temp": 8,
        "summary": "few clouds",
        "icon": "partly-cloudy-night"
      },
      {
        "hour": "00:00",
        "temp": 7,
        "summary": "few clouds",
        "icon": "partly-cloudy-night"
      },
      {
        "hour": "01:00",
        "temp": 7,
        "summary": "few clouds",
        "icon": "partly-cloudy-night"
      },
      {
        "hour": "02:00",
        "temp": 7,
        "summary": "clear sky",
        "icon": "clear-night"
      },
      {
        "hour": "03:00",
        "temp": 7,
        "summary": "few clouds",
        "icon": "partly-cloudy-night"
      },
      {
        "hour": "04:00",
        "temp": 7,
        "summary": "few clouds",
        "icon": "partly-cloudy-night"
      },
      {
        "hour": "05:00",
        "temp": 7,
        "summary": "few clouds",
        "icon": "partly-cloudy-night"
      },
      {
        "hour": "06:00",
        "temp": 7,
        "summary": "few clouds",
        "icon": "partly-cloudy-night"
      },
      {
        "hour": "07:00",
        "temp": 7,
        "summary": "clear sky",
        "icon": "clear-night"
      },
      {
        "hour": "08:00",
        "temp": 7,
        "summary": "clear sky",
        "icon": "clear-day"
      },
      {
        "hour": "09:00",
        "temp": 8,
        "summary": "clear sky",
        "icon": "clear-day"
      },
      {
        "hour": "10:00",
        "temp": 10,
        "summary": "clear sky",
        "icon": "clear-day"
      },
      {
        "hour": "11:00",
        "temp": 11,
        "summary": "clear sky",
        "icon": "clear-day"
      },
      {
        "hour": "12:00",
        "temp": 11,
        "summary": "clear sky",
        "icon": "clear-day"
      },
      {
        "hour": "13:00",
        "temp": 12,
        "summary": "clear sky",
        "icon": "clear-day"
      },
      {
        "hour": "14:00",
        "temp": 12,
        "summary": "clear sky",
        "icon": "clear-day"
      },
      {
        "hour": "15:00",
        "temp": 11,
        "summary": "clear sky",
        "icon": "clear-day"
      },
      {
        "hour": "16:00",
        "temp": 11,
        "summary": "clear sky",
        "icon": "clear-day"
      },
      {
        "hour": "17:00",
        "temp": 11,
        "summary": "clear sky",
        "icon": "clear-day"
      }
    ]
  }
]