[
  {
    "source": "ow",
    "current": {
      "icon": "cloudy",
      "temp": 16,
      "summary": "broken clouds",
      "windDir": 23,
      "humidity": 63,
      "pressure": 1018,
      "feelsLike": 15,
      "windSpeed": 0.45,
      "cloudCover": 72,
      "visibility": 10,
      "percipitation": 0
    },
    "forecast": [
      {
        "date": 1654081200,
        "maxTemp": 21,
        "minTemp": 9,
        "sunrise": "05:52",
        "sunset": "21:46",
        "summary": "scattered clouds",
        "windSpeed": 4.01,
        "windDir": 348,
        "percipitation": 0,
        "humidity": 42,
        "pressure": 1016,
        "cloudCover": 28,
        "dewPoint": 6,
        "chancePrecipitation": 0,
        "chanceRain": 0,
        "chanceSnow": 0,
        "chanceThunder": 0,
        "chanceSleet": 0,
        "icon": "cloudy",
        "day": "Wednesday",
        "dayShort": "Wed"
      },
      {
        "date": 1654167600,
        "maxTemp": 23,
        "minTemp": 10,
        "sunrise": "05:52",
        "sunset": "21:47",
        "summary": "overcast clouds",
        "windSpeed": 4.42,
        "windDir": 79,
        "percipitation": 0,
        "humidity": 39,
        "pressure": 1019,
        "cloudCover": 88,
        "dewPoint": 6,
        "chancePrecipitation": 9,
        "chanceRain": 0,
        "chanceSnow": 0,
        "chanceThunder": 0,
        "chanceSleet": 0,
        "icon": "cloudy",
        "day": "Thursday",
        "dayShort": "Thu"
      },
      {
        "date": 1654254000,
        "maxTemp": 25,
        "minTemp": 14,
        "sunrise": "05:51",
        "sunset": "21:48",
        "summary": "light rain",
        "windSpeed": 3.04,
        "windDir": 65,
        "percipitation": 2.82,
        "humidity": 56,
        "pressure": 1015,
        "cloudCover": 100,
        "dewPoint": 14,
        "chancePrecipitation": 98,
        "chanceRain": 0,
        "chanceSnow": 0,
        "chanceThunder": 0,
        "chanceSleet": 0,
        "icon": "rain",
        "day": "Friday",
        "dayShort": "Fri"
      },
      {
        "date": 1654340400,
        "maxTemp": 28,
        "minTemp": 16,
        "sunrise": "05:50",
        "sunset": "21:49",
        "summary": "moderate rain",
        "windSpeed": 3.65,
        "windDir": 220,
        "percipitation": 6.11,
        "humidity": 52,
        "pressure": 1017,
        "cloudCover": 10,
        "dewPoint": 15,
        "chancePrecipitation": 100,
        "chanceRain": 0,
        "chanceSnow": 0,
        "chanceThunder": 0,
        "chanceSleet": 0,
        "icon": "rain",
        "day": "Saturday",
        "dayShort": "Sat"
      },
      {
        "date": 1654426800,
        "maxTemp": 20,
        "minTemp": 14,
        "sunrise": "05:50",
        "sunset": "21:50",
        "summary": "moderate rain",
        "windSpeed": 6.18,
        "windDir": 247,
        "percipitation": 14.06,
        "humidity": 86,
        "pressure": 1014,
        "cloudCover": 93,
        "dewPoint": 16,
        "chancePrecipitation": 100,
        "chanceRain": 0,
        "chanceSnow": 0,
        "chanceThunder": 0,
        "chanceSleet": 0,
        "icon": "rain",
        "day": "Sunday",
        "dayShort": "Sun"
      },
      {
        "date": 1654513200,
        "maxTemp": 14,
        "minTemp": 11,
        "sunrise": "05:49",
        "sunset": "21:51",
        "summary": "light rain",
        "windSpeed": 6.31,
        "windDir": 279,
        "percipitation": 1.17,
        "humidity": 90,
        "pressure": 1017,
        "cloudCover": 100,
        "dewPoint": 10,
        "chancePrecipitation": 100,
        "chanceRain": 0,
        "chanceSnow": 0,
        "chanceThunder": 0,
        "chanceSleet": 0,
        "icon": "rain",
        "day": "Monday",
        "dayShort": "Mon"
      },
      {
        "date": 1654599600,
        "maxTemp": 22,
        "minTemp": 9,
        "sunrise": "05:49",
        "sunset": "21:52",
        "summary": "few clouds",
        "windSpeed": 3.41,
        "windDir": 288,
        "percipitation": 0,
        "humidity": 44,
        "pressure": 1021,
        "cloudCover": 14,
        "dewPoint": 8,
        "chancePrecipitation": 0,
        "chanceRain": 0,
        "chanceSnow": 0,
        "chanceThunder": 0,
        "chanceSleet": 0,
        "icon": "partly-cloudy-day",
        "day": "Tuesday",
        "dayShort": "Tue"
      },
      {
        "date": 1654686000,
        "maxTemp": 26,
        "minTemp": 15,
        "sunrise": "05:49",
        "sunset": "21:52",
        "summary": "broken clouds",
        "windSpeed": 3.69,
        "windDir": 265,
        "percipitation": 0,
        "humidity": 48,
        "pressure": 1019,
        "cloudCover": 74,
        "dewPoint": 12,
        "chancePrecipitation": 0,
        "chanceRain": 0,
        "chanceSnow": 0,
        "chanceThunder": 0,
        "chanceSleet": 0,
        "icon": "cloudy",
        "day": "Wednesday",
        "dayShort": "Wed"
      }
    ],
    "timezone": "Europe/Paris",
    "nextHours": [
      {
        "hour": "23:00",
        "temp": 16,
        "summary": "broken clouds",
        "icon": "cloudy"
      },
      {
        "hour": "00:00",
        "temp": 15,
        "summary": "broken clouds",
        "icon": "cloudy"
      },
      {
        "hour": "01:00",
        "temp": 14,
        "summary": "broken clouds",
        "icon": "cloudy"
      },
      {
        "hour": "02:00",
        "temp": 13,
        "summary": "broken clouds",
        "icon": "cloudy"
      },
      {
        "hour": "03:00",
        "temp": 12,
        "summary": "few clouds",
        "icon": "partly-cloudy-night"
      },
      {
        "hour": "04:00",
        "temp": 10,
        "summary": "clear sky",
        "icon": "clear-night"
      },
      {
        "hour": "05:00",
        "temp": 10,
        "summary": "few clouds",
        "icon": "partly-cloudy-night"
      },
      {
        "hour": "06:00",
        "temp": 10,
        "summary": "scattered clouds",
        "icon": "cloudy"
      },
      {
        "hour": "07:00",
        "temp": 10,
        "summary": "scattered clouds",
        "icon": "cloudy"
      },
      {
        "hour": "08:00",
        "temp": 12,
        "summary": "broken clouds",
        "icon": "cloudy"
      },
      {
        "hour": "09:00",
        "temp": 14,
        "summary": "overcast clouds",
        "icon": "cloudy"
      },
      {
        "hour": "10:00",
        "temp": 16,
        "summary": "broken clouds",
        "icon": "cloudy"
      },
      {
        "hour": "11:00",
        "temp": 18,
        "summary": "broken clouds",
        "icon": "cloudy"
      },
      {
        "hour": "12:00",
        "temp": 20,
        "summary": "overcast clouds",
        "icon": "cloudy"
      },
      {
        "hour": "13:00",
        "temp": 21,
        "summary": "overcast clouds",
        "icon": "cloudy"
      },
      {
        "hour": "14:00",
        "temp": 22,
        "summary": "overcast clouds",
        "icon": "cloudy"
      },
      {
        "hour": "15:00",
        "temp": 23,
        "summary": "overcast clouds",
        "icon": "cloudy"
      },
      {
        "hour": "16:00",
        "temp": 23,
        "summary": "overcast clouds",
        "icon": "cloudy"
      },
      {
        "hour": "17:00",
        "temp": 23,
        "summary": "broken clouds",
        "icon": "cloudy"
      },
      {
        "hour": "18:00",
        "temp": 23,
        "summary": "broken clouds",
        "icon": "cloudy"
      },
      {
        "hour": "19:00",
        "temp": 23,
        "summary": "broken clouds",
        "icon": "cloudy"
      },
      {
        "hour": "20:00",
        "temp": 22,
        "summary": "broken clouds",
        "icon": "cloudy"
      },
      {
        "hour": "21:00",
        "temp": 20,
        "summary": "overcast clouds",
        "icon": "cloudy"
      },
      {
        "hour": "22:00",
        "temp": 18,
        "summary": "broken clouds",
        "icon": "cloudy"
      }
    ]
  },
  {
    "source": "ow",
    "current": {
      "icon": "clear-night",
      "temp": 17,
      "summary": "clear sky",
      "windDir": 20,
      "humidity": 54,
      "pressure": 1017,
      "feelsLike": 17,
      "windSpeed": 5.14,
      "cloudCover": 0,
      "visibility": 10,
      "percipitation": 0
    },
    "forecast": [
      {
        "date": 1654081200,
        "maxTemp": 21,
        "minTemp": 10,
        "sunrise": "05:51",
        "sunset": "21:45",
        "summary": "scattered clouds",
        "windSpeed": 3.77,
        "windDir": 20,
        "percipitation": 0,
        "humidity": 39,
        "pressure": 1016,
        "cloudCover": 36,
        "dewPoint": 6,
        "chancePrecipitation": 0,
        "chanceRain": 0,
        "chanceSnow": 0,
        "chanceThunder": 0,
        "chanceSleet": 0,
        "icon": "cloudy",
        "day": "Wednesday",
        "dayShort": "Wed"
      },
      {
        "date": 1654167600,
        "maxTemp": 23,
        "minTemp": 10,
        "sunrise": "05:51",
        "sunset": "21:46",
        "summary": "overcast clouds",
        "windSpeed": 4.3,
        "windDir": 78,
        "percipitation": 0,
        "humidity": 41,
        "pressure": 1019,
        "cloudCover": 86,
        "dewPoint": 7,
        "chancePrecipitation": 8,
        "chanceRain": 0,
        "chanceSnow": 0,
        "chanceThunder": 0,
        "chanceSleet": 0,
        "icon": "cloudy",
        "day": "Thursday",
        "dayShort": "Thu"
      },
      {
        "date": 1654254000,
        "maxTemp": 25,
        "minTemp": 14,
        "sunrise": "05:50",
        "sunset": "21:47",
        "summary": "light rain",
        "windSpeed": 3.34,
        "windDir": 219,
        "percipitation": 1.12,
        "humidity": 60,
        "pressure": 1015,
        "cloudCover": 100,
        "dewPoint": 14,
        "chancePrecipitation": 88,
        "chanceRain": 0,
        "chanceSnow": 0,
        "chanceThunder": 0,
        "chanceSleet": 0,
        "icon": "rain",
        "day": "Friday",
        "dayShort": "Fri"
      },
      {
        "date": 1654340400,
        "maxTemp": 28,
        "minTemp": 15,
        "sunrise": "05:50",
        "sunset": "21:48",
        "summary": "moderate rain",
        "windSpeed": 3.01,
        "windDir": 200,
        "percipitation": 4.98,
        "humidity": 51,
        "pressure": 1017,
        "cloudCover": 1,
        "dewPoint": 15,
        "chancePrecipitation": 100,
        "chanceRain": 0,
        "chanceSnow": 0,
        "chanceThunder": 0,
        "chanceSleet": 0,
        "icon": "rain",
        "day": "Saturday",
        "dayShort": "Sat"
      },
      {
        "date": 1654426800,
        "maxTemp": 21,
        "minTemp": 14,
        "sunrise": "05:49",
        "sunset": "21:48",
        "summary": "moderate rain",
        "windSpeed": 5.92,
        "windDir": 245,
        "percipitation": 18.97,
        "humidity": 85,
        "pressure": 1014,
        "cloudCover": 83,
        "dewPoint": 16,
        "chancePrecipitation": 100,
        "chanceRain": 0,
        "chanceSnow": 0,
        "chanceThunder": 0,
        "chanceSleet": 0,
        "icon": "rain",
        "day": "Sunday",
        "dayShort": "Sun"
      },
      {
        "date": 1654513200,
        "maxTemp": 15,
        "minTemp": 11,
        "sunrise": "05:49",
        "sunset": "21:49",
        "summary": "light rain",
        "windSpeed": 5.88,
        "windDir": 219,
        "percipitation": 1.31,
        "humidity": 88,
        "pressure": 1017,
        "cloudCover": 100,
        "dewPoint": 10,
        "chancePrecipitation": 100,
        "chanceRain": 0,
        "chanceSnow": 0,
        "chanceThunder": 0,
        "chanceSleet": 0,
        "icon": "rain",
        "day": "Monday",
        "dayShort": "Mon"
      },
      {
        "date": 1654599600,
        "maxTemp": 23,
        "minTemp": 10,
        "sunrise": "05:48",
        "sunset": "21:50",
        "summary": "few clouds",
        "windSpeed": 3.43,
        "windDir": 287,
        "percipitation": 0,
        "humidity": 43,
        "pressure": 1021,
        "cloudCover": 12,
        "dewPoint": 8,
        "chancePrecipitation": 0,
        "chanceRain": 0,
        "chanceSnow": 0,
        "chanceThunder": 0,
        "chanceSleet": 0,
        "icon": "partly-cloudy-day",
        "day": "Tuesday",
        "dayShort": "Tue"
      },
      {
        "date": 1654686000,
        "maxTemp": 26,
        "minTemp": 15,
        "sunrise": "05:48",
        "sunset": "21:51",
        "summary": "broken clouds",
        "windSpeed": 3.25,
        "windDir": 255,
        "percipitation": 0,
        "humidity": 42,
        "pressure": 1019,
        "cloudCover": 65,
        "dewPoint": 11,
        "chancePrecipitation": 0,
        "chanceRain": 0,
        "chanceSnow": 0,
        "chanceThunder": 0,
        "chanceSleet": 0,
        "icon": "cloudy",
        "day": "Wednesday",
        "dayShort": "Wed"
      }
    ],
    "timezone": "Europe/Paris",
    "nextHours": [
      {
        "hour": "22:00",
        "temp": 17,
        "summary": "clear sky",
        "icon": "clear-night"
      },
      {
        "hour": "23:00",
        "temp": 17,
        "summary": "few clouds",
        "icon": "partly-cloudy-night"
      },
      {
        "hour": "00:00",
        "temp": 16,
        "summary": "few clouds",
        "icon": "partly-cloudy-night"
      },
      {
        "hour": "01:00",
        "temp": 14,
        "summary": "scattered clouds",
        "icon": "cloudy"
      },
      {
        "hour": "02:00",
        "temp": 13,
        "summary": "scattered clouds",
        "icon": "cloudy"
      },
      {
        "hour": "03:00",
        "temp": 11,
        "summary": "clear sky",
        "icon": "clear-night"
      },
      {
        "hour": "04:00",
        "temp": 11,
        "summary": "clear sky",
        "icon": "clear-night"
      },
      {
        "hour": "05:00",
        "temp": 10,
        "summary": "few clouds",
        "icon": "partly-cloudy-night"
      },
      {
        "hour": "06:00",
        "temp": 10,
        "summary": "scattered clouds",
        "icon": "cloudy"
      },
      {
        "hour": "07:00",
        "temp": 10,
        "summary": "scattered clouds",
        "icon": "cloudy"
      },
      {
        "hour": "08:00",
        "temp": 12,
        "summary": "broken clouds",
        "icon": "cloudy"
      },
      {
        "hour": "09:00",
        "temp": 14,
        "summary": "overcast clouds",
        "icon": "cloudy"
      },
      {
        "hour": "10:00",
        "temp": 16,
        "summary": "broken clouds",
        "icon": "cloudy"
      },
      {
        "hour": "11:00",
        "temp": 18,
        "summary": "broken clouds",
        "icon": "cloudy"
      },
      {
        "hour": "12:00",
        "temp": 20,
        "summary": "broken clouds",
        "icon": "cloudy"
      },
      {
        "hour": "13:00",
        "temp": 21,
        "summary": "overcast clouds",
        "icon": "cloudy"
      },
      {
        "hour": "14:00",
        "temp": 22,
        "summary": "overcast clouds",
        "icon": "cloudy"
      },
      {
        "hour": "15:00",
        "temp": 23,
        "summary": "broken clouds",
        "icon": "cloudy"
      },
      {
        "hour": "16:00",
        "temp": 23,
        "summary": "broken clouds",
        "icon": "cloudy"
      },
      {
        "hour": "17:00",
        "temp": 23,
        "summary": "broken clouds",
        "icon": "cloudy"
      },
      {
        "hour": "18:00",
        "temp": 23,
        "summary": "broken clouds",
        "icon": "cloudy"
      },
      {
        "hour": "19:00",
        "temp": 22,
        "summary": "broken clouds",
        "icon": "cloudy"
      },
      {
        "hour": "20:00",
        "temp": 22,
        "summary": "scattered clouds",
        "icon": "cloudy"
      },
      {
        "hour": "21:00",
        "temp": 20,
        "summary": "overcast clouds",
        "icon": "cloudy"
      }
    ]
  },
  {
    "source": "ow",
    "current": {
      "icon": "cloudy",
      "temp": 14,
      "summary": "overcast clouds",
      "windDir": 64,
      "humidity": 84,
      "pressure": 1019,
      "feelsLike": 14,
      "windSpeed": 4.77,
      "cloudCover": 100,
      "visibility": 10,
      "percipitation": 0
    },
    "forecast": [
      {
        "date": 1654084800,
        "maxTemp": 15,
        "minTemp": 11,
        "sunrise": "06:06",
        "sunset": "22:04",
        "summary": "few clouds",
        "windSpeed": 5.06,
        "windDir": 333,
        "percipitation": 0,
        "humidity": 65,
        "pressure": 1018,
        "cloudCover": 11,
        "dewPoint": 8,
        "chancePrecipitation": 0,
        "chanceRain": 0,
        "chanceSnow": 0,
        "chanceThunder": 0,
        "chanceSleet": 0,
        "icon": "partly-cloudy-day",
        "day": "Wednesday",
        "dayShort": "Wed"
      },
      {
        "date": 1654171200,
        "maxTemp": 18,
        "minTemp": 10,
        "sunrise": "06:05",
        "sunset": "22:05",
        "summary": "broken clouds",
        "windSpeed": 6.56,
        "windDir": 75,
        "percipitation": 0,
        "humidity": 61,
        "pressure": 1018,
        "cloudCover": 83,
        "dewPoint": 10,
        "chancePrecipitation": 22,
        "chanceRain": 0,
        "chanceSnow": 0,
        "chanceThunder": 0,
        "chanceSleet": 0,
        "icon": "cloudy",
        "day": "Thursday",
        "dayShort": "Thu"
      },
      {
        "date": 1654257600,
        "maxTemp": 20,
        "minTemp": 14,
        "sunrise": "06:04",
        "sunset": "22:05",
        "summary": "light rain",
        "windSpeed": 5.79,
        "windDir": 56,
        "percipitation": 0.63,
        "humidity": 61,
        "pressure": 1015,
        "cloudCover": 71,
        "dewPoint": 12,
        "chancePrecipitation": 60,
        "chanceRain": 0,
        "chanceSnow": 0,
        "chanceThunder": 0,
        "chanceSleet": 0,
        "icon": "rain",
        "day": "Friday",
        "dayShort": "Fri"
      },
      {
        "date": 1654344000,
        "maxTemp": 18,
        "minTemp": 12,
        "sunrise": "06:04",
        "sunset": "22:06",
        "summary": "light rain",
        "windSpeed": 4.33,
        "windDir": 51,
        "percipitation": 0.15,
        "humidity": 84,
        "pressure": 1017,
        "cloudCover": 23,
        "dewPoint": 13,
        "chancePrecipitation": 58,
        "chanceRain": 0,
        "chanceSnow": 0,
        "chanceThunder": 0,
        "chanceSleet": 0,
        "icon": "rain",
        "day": "Saturday",
        "dayShort": "Sat"
      },
      {
        "date": 1654430400,
        "maxTemp": 15,
        "minTemp": 14,
        "sunrise": "06:03",
        "sunset": "22:07",
        "summary": "light rain",
        "windSpeed": 7.01,
        "windDir": 261,
        "percipitation": 8.47,
        "humidity": 96,
        "pressure": 1014,
        "cloudCover": 100,
        "dewPoint": 14,
        "chancePrecipitation": 100,
        "chanceRain": 0,
        "chanceSnow": 0,
        "chanceThunder": 0,
        "chanceSleet": 0,
        "icon": "rain",
        "day": "Sunday",
        "dayShort": "Sun"
      },
      {
        "date": 1654516800,
        "maxTemp": 15,
        "minTemp": 11,
        "sunrise": "06:03",
        "sunset": "22:08",
        "summary": "light rain",
        "windSpeed": 7.8,
        "windDir": 301,
        "percipitation": 1.38,
        "humidity": 64,
        "pressure": 1019,
        "cloudCover": 92,
        "dewPoint": 8,
        "chancePrecipitation": 84,
        "chanceRain": 0,
        "chanceSnow": 0,
        "chanceThunder": 0,
        "chanceSleet": 0,
        "icon": "rain",
        "day": "Monday",
        "dayShort": "Mon"
      },
      {
        "date": 1654603200,
        "maxTemp": 16,
        "minTemp": 14,
        "sunrise": "06:02",
        "sunset": "22:09",
        "summary": "overcast clouds",
        "windSpeed": 3.92,
        "windDir": 249,
        "percipitation": 0,
        "humidity": 74,
        "pressure": 1022,
        "cloudCover": 85,
        "dewPoint": 11,
        "chancePrecipitation": 0,
        "chanceRain": 0,
        "chanceSnow": 0,
        "chanceThunder": 0,
        "chanceSleet": 0,
        "icon": "cloudy",
        "day": "Tuesday",
        "dayShort": "Tue"
      },
      {
        "date": 1654689600,
        "maxTemp": 17,
        "minTemp": 15,
        "sunrise": "06:02",
        "sunset": "22:10",
        "summary": "broken clouds",
        "windSpeed": 6.41,
        "windDir": 210,
        "percipitation": 0,
        "humidity": 83,
        "pressure": 1019,
        "cloudCover": 72,
        "dewPoint": 14,
        "chancePrecipitation": 2,
        "chanceRain": 0,
        "chanceSnow": 0,
        "chanceThunder": 0,
        "chanceSleet": 0,
        "icon": "cloudy",
        "day": "Wednesday",
        "dayShort": "Wed"
      }
    ],
    "timezone": "Europe/Paris",
    "nextHours": [
      {
        "hour": "23:00",
        "temp": 14,
        "summary": "overcast clouds",
        "icon": "cloudy"
      },
      {
        "hour": "00:00",
        "temp": 13,
        "summary": "overcast clouds",
        "icon": "cloudy"
      },
      {
        "hour": "01:00",
        "temp": 13,
        "summary": "overcast clouds",
        "icon": "cloudy"
      },
      {
        "hour": "02:00",
        "temp": 12,
        "summary": "overcast clouds",
        "icon": "cloudy"
      },
      {
        "hour": "03:00",
        "temp": 11,
        "summary": "broken clouds",
        "icon": "cloudy"
      },
      {
        "hour": "04:00",
        "temp": 10,
        "summary": "broken clouds",
        "icon": "cloudy"
      },
      {
        "hour": "05:00",
        "temp": 10,
        "summary": "overcast clouds",
        "icon": "cloudy"
      },
      {
        "hour": "06:00",
        "temp": 10,
        "summary": "overcast clouds",
        "icon": "cloudy"
      },
      {
        "hour": "07:00",
        "temp": 10,
        "summary": "overcast clouds",
        "icon": "cloudy"
      },
      {
        "hour": "08:00",
        "temp": 11,
        "summary": "overcast clouds",
        "icon": "cloudy"
      },
      {
        "hour": "09:00",
        "temp": 13,
        "summary": "overcast clouds",
        "icon": "cloudy"
      },
      {
        "hour": "10:00",
        "temp": 14,
        "summary": "overcast clouds",
        "icon": "cloudy"
      },
      {
        "hour": "11:00",
        "temp": 16,
        "summary": "overcast clouds",
        "icon": "cloudy"
      },
      {
        "hour": "12:00",
        "temp": 16,
        "summary": "overcast clouds",
        "icon": "cloudy"
      },
      {
        "hour": "13:00",
        "temp": 17,
        "summary": "overcast clouds",
        "icon": "cloudy"
      },
      {
        "hour": "14:00",
        "temp": 17,
        "summary": "broken clouds",
        "icon": "cloudy"
      },
      {
        "hour": "15:00",
        "temp": 18,
        "summary": "scattered clouds",
        "icon": "cloudy"
      },
      {
        "hour": "16:00",
        "temp": 18,
        "summary": "scattered clouds",
        "icon": "cloudy"
      },
      {
        "hour": "17:00",
        "temp": 18,
        "summary": "broken clouds",
        "icon": "cloudy"
      },
      {
        "hour": "18:00",
        "temp": 17,
        "summary": "broken clouds",
        "icon": "cloudy"
      },
      {
        "hour": "19:00",
        "temp": 16,
        "summary": "broken clouds",
        "icon": "cloudy"
      },
      {
        "hour": "20:00",
        "temp": 15,
        "summary": "broken clouds",
        "icon": "cloudy"
      },
      {
        "hour": "21:00",
        "temp": 14,
        "summary": "overcast clouds",
        "icon": "cloudy"
      },
      {
        "hour": "22:00",
        "temp": 14,
        "summary": "overcast clouds",
        "icon": "cloudy"
      }
    ]
  }
]